[
  {
    "day": 1,
    "delivered": [
      [
        0.0,
        551.5656298038751,
        0.0,
        0.0
      ],
      [
        595.390453146351,
        0.0,
        0.0,
        0.0
      ]
    ],
    "transmit": [
      [
        0.0,
        1200.0,
        0.0,
        0.0
      ],
      [
        1200.0,
        0.0,
        0.0,
        0.0
      ]
    ],
    "donor_ids": [
      "RF1",
      "RF2"
    ],
    "recipient_ids": [
      "RF3",
      "RF4",
      "RF5",
      "RF6"
    ],
    "eta": [
      [
        0.421394870737647,
        0.4596380248365626,
        0.39197774658697965,
        0.33939419585388453
      ],
      [
        0.4961587109552925,
        0.44101354695732975,
        0.3805187860216065,
        0.3391710109681253
      ]
    ],
    "objective": -1146.9536829502263
  },
  {
    "day": 2,
    "delivered": [
      [
        0.0,
        551.5656298038751,
        0.0,
        0.0
      ],
      [
        595.390453146351,
        0.0,
        0.0,
        0.0
      ]
    ],
    "transmit": [
      [
        0.0,
        1200.0,
        0.0,
        0.0
      ],
      [
        1200.0,
        0.0,
        0.0,
        0.0
      ]
    ],
    "donor_ids": [
      "RF1",
      "RF2"
    ],
    "recipient_ids": [
      "RF3",
      "RF4",
      "RF5",
      "RF6"
    ],
    "eta": [
      [
        0.421394870737647,
        0.4596380248365626,
        0.39197774658697965,
        0.33939419585388453
      ],
      [
        0.4961587109552925,
        0.44101354695732975,
        0.3805187860216065,
        0.3391710109681253
      ]
    ],
    "objective": -1146.9536829502263
  },
  {
    "day": 3,
    "delivered": [
      [
        0.0,
        551.5656298038751,
        0.0,
        0.0
      ],
      [
        595.390453146351,
        0.0,
        0.0,
        0.0
      ]
    ],
    "transmit": [
      [
        0.0,
        1200.0,
        0.0,
        0.0
      ],
      [
        1200.0,
        0.0,
        0.0,
        0.0
      ]
    ],
    "donor_ids": [
      "RF1",
      "RF2"
    ],
    "recipient_ids": [
      "RF3",
      "RF4",
      "RF5",
      "RF6"
    ],
    "eta": [
      [
        0.421394870737647,
        0.4596380248365626,
        0.39197774658697965,
        0.33939419585388453
      ],
      [
        0.4961587109552925,
        0.44101354695732975,
        0.3805187860216065,
        0.3391710109681253
      ]
    ],
    "objective": -1146.9536829502263
  }
]